pyp/__init__.py
pyp-3.0.7.data/scripts/pyp
pyp-3.0.7.dist-info/LICENSE
pyp-3.0.7.dist-info/METADATA
pyp-3.0.7.dist-info/WHEEL
pyp-3.0.7.dist-info/top_level.txt
pyp-3.0.7.dist-info/RECORD
