Metadata-Version: 2.1
Name: pyp
Version: 3.0.7
Summary: Python Power at the Prompt
Home-page: https://thepyedpiper.github.io/pyp/
Author: Toby Rosen
Author-email: thepyedpiper@gmail.com
License: UNKNOWN
Project-URL: Bug Tracker, https://github.com/thepyedpiper/pyp/issues
Platform: UNKNOWN
Classifier: Programming Language :: Python :: 3
Classifier: License :: OSI Approved :: BSD License
Classifier: Operating System :: OS Independent
Requires-Python: >=3.0
License-File: LICENSE
